MANIFEST.in
README.md
setup.py
mb_cool_library/__init__.py
mb_cool_library/rek.py
mb_cool_library.egg-info/PKG-INFO
mb_cool_library.egg-info/SOURCES.txt
mb_cool_library.egg-info/dependency_links.txt
mb_cool_library.egg-info/top_level.txt