Metadata-Version: 1.0
Name: mb-cool-library
Version: 0.1.4
Summary: Test test test
Home-page: UNKNOWN
Author: MB
Author-email: mb@dev.pl
License: UNKNOWN
Platform: UNKNOWN
